imwatchingyou/__init__.py
imwatchingyou/imwatchingyou.py
imwatchingyou-2.3.0.dist-info/METADATA
imwatchingyou-2.3.0.dist-info/WHEEL
imwatchingyou-2.3.0.dist-info/top_level.txt
imwatchingyou-2.3.0.dist-info/RECORD
