Metadata-Version: 2.1
Name: imwatchingyou
Version: 2.3.0
Summary: A Python GUI-based Python debugger enabling realtime watching and modification of variables and expressions, plus a REPL-light
Home-page: https://github.com/PySimpleGUI/imwatchingyou
Author: PySimpleGUI
Author-email: mike@PySimpleGUI.org
License: UNKNOWN
Keywords: GUI UI PySimpleGUI tkinter
Platform: UNKNOWN
Classifier: Programming Language :: Python :: 3
Classifier: Programming Language :: Python :: 3.4
Classifier: Programming Language :: Python :: 3.5
Classifier: Programming Language :: Python :: 3.6
Classifier: Programming Language :: Python :: 3.7
Classifier: License :: OSI Approved :: GNU Lesser General Public License v3 or later (LGPLv3+)
Classifier: Topic :: Multimedia :: Graphics
Classifier: Operating System :: OS Independent
Requires-Dist: PySimpleGUI
